{
  "$type": "VfDa",
  "gon": "Vfx_Head",
  "vfxsp": {
    "$type": "[GaOb]$",
    "guid": "",
    "TypeName": null
  },
  "vfxspc": {
    "$type": "[GaOb]$",
    "guid": "",
    "TypeName": null
  },
  "vfxp": {
    "$type": "[GaOb]$",
    "guid": "c8bf770eba27d484aae96538dd8037b1",
    "TypeName": "GaOb"
  },
  "vfxpc": {
    "$type": "[GaOb]$",
    "guid": "",
    "TypeName": null
  },
  "vfxlp": {
    "$type": "[GaOb]$",
    "guid": "",
    "TypeName": null
  },
  "vfxlpc": {
    "$type": "[GaOb]$",
    "guid": "",
    "TypeName": null
  },
  "fgo": true,
  "stgo": false,
  "ss": 7500000,
  "ms": 10000000,
  "ls": 12999999,
  "lpx": false,
  "lpy": false,
  "lpz": false,
  "lrx": false,
  "lry": false,
  "lrz": false,
  "irx": false,
  "iry": false,
  "irz": false
}