{
  "$type": "CrStDa, x",
  "r": {
    "$type": "[RaStDa]@, x",
    "guid": "953e566d6ae6f5d4091b8a9b603494d6",
    "TypeName": "RaStDa"
  },
  "s": {
    "$type": "[Si]@, x",
    "guid": "666d13b66e2389144a8bba7529af4e29",
    "TypeName": "Si"
  },
  "dn": "baryonyx2",
  "lkn": "IDS_BARYONYX2",
  "a": "DINODESC_BODY_BARYONYX2",
  "i": {
    "$type": "[Sp]$, x",
    "guid": "3cf42aef55719ba488dbf4d7424caebd",
    "TypeName": "Sp"
  },
  "att": {
    "$type": "[CrAtDa]@, x",
    "guid": "8c9272be3a274c74e9618088815d9007",
    "TypeName": "CrAtDa"
  },
  "dna": {
    "$type": "[CrDNARe]@, x",
    "guid": "1f97ac17a0380e94fb868195c0dbb85f",
    "TypeName": "CrDNARe"
  },
  "fm": {
    "$type": "[FaStDa]@, x",
    "guid": "43da83e862ff6354495dfb1caccce6ff",
    "TypeName": "FaStDa"
  },
  "g": {
    "$type": "[RPSStDa]@, x",
    "guid": "423ea1736c538ec448dc6b1ba22940f0",
    "TypeName": "RPSStDa"
  },
  "cs": {
    "$type": "[ChShStDa]@, x",
    "guid": "171bab3d4a3de214ba23798b35d68fd4",
    "TypeName": "ChShStDa"
  },
  "b": {
    "$type": "[BaCrStDa]@, x",
    "guid": "106374a009f2dd54491ff2a03d2a5586",
    "TypeName": "BaCrStDa"
  },
  "rc": {
    "$type": "[RaCrStDa]@, x",
    "guid": "0d01dcfd3c87e8344bd796b1c1e80046",
    "TypeName": "RaCrStDa"
  },
  "dc": {
    "$type": "[DrCrStDa]@, x",
    "guid": "43be460b31ed68048a41d6e91b9cd0d7",
    "TypeName": "DrCrStDa"
  },
  "ac": {
    "$type": "AbIt, x",
    "ai": {
      "$type": "[AbStDa]@, x",
      "guid": "",
      "TypeName": "AbStDa"
    },
    "at": 3000,
    "rst": -1
  },
  "al": [
    {
      "$type": "AbIt, x",
      "ai": {
        "$type": "[AbStDa]@, x",
        "guid": "69e01c9e17ff8c749954273cae24042f",
        "TypeName": "AbStDa"
      },
      "at": 3800,
      "rst": 2467
    },
    {
      "$type": "AbIt, x",
      "ai": {
        "$type": "[AbStDa]@, x",
        "guid": "43aea8edbb83bf14d996870b928a8fac",
        "TypeName": "AbStDa"
      },
      "at": 3233,
      "rst": 2266
    },
    {
      "$type": "AbIt, x",
      "ai": {
        "$type": "[AbStDa]@, x",
        "guid": "25e3820331f463142bc7c618296056ae",
        "TypeName": "AbStDa"
      },
      "at": 3400,
      "rst": 2000
    }
  ],
  "pl": [],
  "dep": false,
  "eb": true,
  "daid": false,
  "el": true,
  "eg": true,
  "ua": 100,
  "rs": 100,
  "so": 901,
  "sfx": {
    "$type": "[CrSfDa]@, x",
    "guid": "",
    "TypeName": "CrSfDa"
  },
  "sfxf": {
    "$type": "[CSDa]@, x",
    "guid": "",
    "TypeName": "CSDa"
  },
  "HoloMaterial": {
    "$type": "[Ma]$, x",
    "guid": "f4ca8a3af6a64cb4da5313fd2a8bb351",
    "TypeName": "Ma"
  },
  "hrl": 2000,
  "drl": 2233,
  "swl": 2367
}