{
  "$type": "AbStDa",
  "n": "IDS_TIP_ABILITY_TITLE_FIELDCLEAR",
  "d": "IDS_ABILITY_LONG_DESC_FIELDCLEAR",
  "sd": "IDS_TIP_ABILITY_FIELDCLEAR",
  "i": {
    "$type": "[Sp]$",
    "guid": "ad1259d6390aa7342acaf74c7f0c2b76",
    "TypeName": "Sp"
  },
  "cod": 0,
  "cu": 0,
  "c": 2,
  "pri": "n",
  "bl": [
    {
      "$type": "BeIt",
      "b": {
        "$type": "[BeDa]@",
        "guid": "f528a7b2423658442ac73c78031e7c8f",
        "TypeName": "BeDaBaDa"
      }
    },
    {
      "$type": "BeIt",
      "b": {
        "$type": "[BeDa]@",
        "guid": "b6b7f4d0dee90fd42bb3cbf0249c017d",
        "TypeName": "BeEfInReHaFoSwDa"
      }
    }
  ],
  "uc": true
}